nsdget/__init__.py
nsdget/core.py
nsdget-0.0.4.dist-info/METADATA
nsdget-0.0.4.dist-info/WHEEL
nsdget-0.0.4.dist-info/entry_points.txt
nsdget-0.0.4.dist-info/RECORD
