Metadata-Version: 2.4
Name: nsdget
Version: 0.0.4
Summary: Python API to easily download stimuli and fMRI betas from Natural Scenes Dataset.
Author-email: xnought <drbertucci@hotmail.com>
Requires-Python: >=3.10
Requires-Dist: colored>=2.3.0
Requires-Dist: nibabel>=5.3.2
Requires-Dist: numpy>=2.2.3
Requires-Dist: pandas>=2.2.3
Requires-Dist: pillow>=11.1.0
Requires-Dist: pyarrow>=19.0.1
Requires-Dist: tqdm>=4.67.1
